{
  "status": "success",
  "microtime": 0.038092851638793945,
  "dateTime": "2024-04-19 18:29:26",
  "error": "",
  "content": {
    "gameLabels": [
      "firekirin",
      "galaxsys",
      "amatic",
      "scientific_games",
      "red_tiger",
      "red_tiger_premium",
      "booming",
      "evolution_lobby",
      "jetx",
      "aviator",
      "live_dealers",
      "rubyplay",
      "fish",
      "sport_betting",
      "novomatic_deluxe",
      "aristocrat",
      "altente",
      "playson",
      "apollo",
      "playngo",
      "kajot",
      "pragmatic",
      "novomatic_html5",
      "tomhorn",
      "microgaming",
      "ainsworth",
      "quickspin",
      "NetEnt",
      "habanero",
      "igt",
      "igrosoft",
      "apex",
      "fast_games",
      "merkur",
      "wazdan",
      "egt",
      "novomatic_classic"
    ],
    "gameTitles": [
      "firekirin",
      "galaxsys",
      "amatic",
      "scientific_games",
      "red_tiger",
      "red_tiger_premium",
      "booming",
      "evolution",
      "fast_games",
      "live_dealers",
      "rubyplay",
      "fish",
      "novomatic",
      "aristocrat",
      "altente",
      "playson",
      "apollo",
      "playngo",
      "kajot",
      "pragmatic",
      "arcade",
      "tomhorn",
      "microgaming",
      "ainsworth",
      "quickspin",
      "NetEnt",
      "netent",
      "habanero",
      "igt",
      "igrosoft",
      "apex",
      "merkur",
      "wazdan",
      "egt",
      "roulette",
      "bingo",
      "keno",
      "table_games"
    ],
    "gameList": [
      {
        "id": "12558",
        "name": "Buffalo 777",
        "name_cn": "",
        "name_kr": "",
        "img": "https://static.cdns-stat.com/resources//sitepicstbs/xgames/game_img_2/buffalo777.jpg",
        "label": "firekirin",
        "device": "2",
        "title": "firekirin",
        "categories": "slots",
        "flash": "0",
        "vertical": "0",
        "bm": "0",
        "demo": "0",
        "localhost": "0",
        "rewriterule": "0",
        "lines": "25",
        "width": "1",
        "wager": "1",
        "bonus": "1",
        "exitButton": "1",
        "disableReload": "1",
        "menu": "",
        "system_name2": "firekirin/buffalo777"
      },
      {
        "id": "12557",
        "name": "God of Fortune",
        "name_cn": "",
        "name_kr": "",
        "img": "https://static.cdns-stat.com/resources//sitepicstbs/xgames/game_img_2/godoffortune.jpg",
        "label": "firekirin",
        "device": "2",
        "title": "firekirin",
        "categories": "slots",
        "flash": "0",
        "vertical": "0",
        "bm": "0",
        "demo": "0",
        "localhost": "0",
        "rewriterule": "0",
        "lines": "25",
        "width": "1",
        "wager": "1",
        "bonus": "1",
        "exitButton": "1",
        "disableReload": "1",
        "menu": "",
        "system_name2": "firekirin/godoffortune"
      },
      {
        "id": "12556",
        "name": "Vegas 7s",
        "name_cn": "",
        "name_kr": "",
        "img": "https://static.cdns-stat.com/resources//sitepicstbs/xgames/game_img_2/vegas7s.jpg",
        "label": "firekirin",
        "device": "2",
        "title": "firekirin",
        "categories": "slots",
        "flash": "0",
        "vertical": "0",
        "bm": "0",
        "demo": "0",
        "localhost": "0",
        "rewriterule": "0",
        "lines": "25",
        "width": "1",
        "wager": "1",
        "bonus": "1",
        "exitButton": "1",
        "disableReload": "1",
        "menu": "",
        "system_name2": "firekirin/vegas7s"
      },
      {
        "id": "12547",
        "name": "Atlantis",
        "name_cn": "",
        "name_kr": "",
        "img": "https://static.cdns-stat.com/resources//sitepicstbs/op_galaxsys/game_img_2/62080.jpg",
        "label": "galaxsys",
        "device": "2",
        "title": "galaxsys",
        "categories": "slots",
        "flash": "0",
        "vertical": "0",
        "bm": "0",
        "demo": "0",
        "localhost": "0",
        "rewriterule": "0",
        "lines": "0",
        "width": "1",
        "wager": "0",
        "bonus": "0",
        "exitButton": "1",
        "disableReload": "0",
        "menu": "",
        "system_name2": "galaxsys/Atlantis"
      },
      {
        "id": "12546",
        "name": "Atlantis",
        "name_cn": "",
        "name_kr": "",
        "img": "https://static.cdns-stat.com/resources//sitepicstbs/op_galaxsys/game_img_2/62079.jpg",
        "label": "galaxsys",
        "device": "2",
        "title": "galaxsys",
        "categories": "slots",
        "flash": "0",
        "vertical": "0",
        "bm": "0",
        "demo": "0",
        "localhost": "0",
        "rewriterule": "0",
        "lines": "0",
        "width": "1",
        "wager": "0",
        "bonus": "0",
        "exitButton": "1",
        "disableReload": "0",
        "menu": "",
        "system_name2": "galaxsys/Atlantis"
      },
      {
        "id": "12545",
        "name": "Bingo Star",
        "name_cn": "",
        "name_kr": "",
        "img": "https://static.cdns-stat.com/resources//sitepicstbs/op_galaxsys/game_img_2/62078.jpg",
        "label": "galaxsys",
        "device": "2",
        "title": "galaxsys",
        "categories": "slots",
        "flash": "0",
        "vertical": "0",
        "bm": "0",
        "demo": "0",
        "localhost": "0",
        "rewriterule": "0",
        "lines": "0",
        "width": "1",
        "wager": "0",
        "bonus": "0",
        "exitButton": "1",
        "disableReload": "0",
        "menu": "",
        "system_name2": "galaxsys/BingoStar"
      },
      {
        "id": "12544",
        "name": "Bingo Star",
        "name_cn": "",
        "name_kr": "",
        "img": "https://static.cdns-stat.com/resources//sitepicstbs/op_galaxsys/game_img_2/62077.jpg",
        "label": "galaxsys",
        "device": "2",
        "title": "galaxsys",
        "categories": "slots",
        "flash": "0",
        "vertical": "0",
        "bm": "0",
        "demo": "0",
        "localhost": "0",
        "rewriterule": "0",
        "lines": "0",
        "width": "1",
        "wager": "0",
        "bonus": "0",
        "exitButton": "1",
        "disableReload": "0",
        "menu": "",
        "system_name2": "galaxsys/BingoStar"
      },
      {
        "id": "12543",
        "name": "Maestro",
        "name_cn": "",
        "name_kr": "",
        "img": "https://static.cdns-stat.com/resources//sitepicstbs/op_galaxsys/game_img_2/62076.jpg",
        "label": "galaxsys",
        "device": "2",
        "title": "galaxsys",
        "categories": "slots",
        "flash": "0",
        "vertical": "0",
        "bm": "0",
        "demo": "0",
        "localhost": "0",
        "rewriterule": "0",
        "lines": "0",
        "width": "1",
        "wager": "0",
        "bonus": "0",
        "exitButton": "1",
        "disableReload": "0",
        "menu": "",
        "system_name2": "galaxsys/Maestro"
      },
      {
        "id": "12542",
        "name": "Maestro",
        "name_cn": "",
        "name_kr": "",
        "img": "https://static.cdns-stat.com/resources//sitepicstbs/op_galaxsys/game_img_2/62075.jpg",
        "label": "galaxsys",
        "device": "2",
        "title": "galaxsys",
        "categories": "slots",
        "flash": "0",
        "vertical": "0",
        "bm": "0",
        "demo": "0",
        "localhost": "0",
        "rewriterule": "0",
        "lines": "0",
        "width": "1",
        "wager": "0",
        "bonus": "0",
        "exitButton": "1",
        "disableReload": "0",
        "menu": "",
        "system_name2": "galaxsys/Maestro"
      },
      {
        "id": "12541",
        "name": "Turbo Mines",
        "name_cn": "",
        "name_kr": "",
        "img": "https://static.cdns-stat.com/resources//sitepicstbs/op_galaxsys/game_img_2/62074.jpg",
        "label": "galaxsys",
        "device": "2",
        "title": "galaxsys",
        "categories": "slots",
        "flash": "0",
        "vertical": "0",
        "bm": "0",
        "demo": "0",
        "localhost": "0",
        "rewriterule": "0",
        "lines": "0",
        "width": "1",
        "wager": "0",
        "bonus": "0",
        "exitButton": "1",
        "disableReload": "0",
        "menu": "",
        "system_name2": "galaxsys/TurboMines"
      },
      {
        "id": "12540",
        "name": "Turbo Mines",
        "name_cn": "",
        "name_kr": "",
        "img": "https://static.cdns-stat.com/resources//sitepicstbs/op_galaxsys/game_img_2/62073.jpg",
        "label": "galaxsys",
        "device": "2",
        "title": "galaxsys",
        "categories": "slots",
        "flash": "0",
        "vertical": "0",
        "bm": "0",
        "demo": "0",
        "localhost": "0",
        "rewriterule": "0",
        "lines": "0",
        "width": "1",
        "wager": "0",
        "bonus": "0",
        "exitButton": "1",
        "disableReload": "0",
        "menu": "",
        "system_name2": "galaxsys/TurboMines"
      },
      {
        "id": "12539",
        "name": "Totem",
        "name_cn": "",
        "name_kr": "",
        "img": "https://static.cdns-stat.com/resources//sitepicstbs/op_galaxsys/game_img_2/62072.jpg",
        "label": "galaxsys",
        "device": "2",
        "title": "galaxsys",
        "categories": "slots",
        "flash": "0",
        "vertical": "0",
        "bm": "0",
        "demo": "0",
        "localhost": "0",
        "rewriterule": "0",
        "lines": "0",
        "width": "1",
        "wager": "0",
        "bonus": "0",
        "exitButton": "1",
        "disableReload": "0",
        "menu": "",
        "system_name2": "galaxsys/Totem"
      },
      {
        "id": "12538",
        "name": "Magic Dice",
        "name_cn": "",
        "name_kr": "",
        "img": "https://static.cdns-stat.com/resources//sitepicstbs/op_galaxsys/game_img_2/62071.jpg",
        "label": "galaxsys",
        "device": "2",
        "title": "galaxsys",
        "categories": "slots",
        "flash": "0",
        "vertical": "0",
        "bm": "0",
        "demo": "0",
        "localhost": "0",
        "rewriterule": "0",
        "lines": "0",
        "width": "1",
        "wager": "0",
        "bonus": "0",
        "exitButton": "1",
        "disableReload": "0",
        "menu": "",
        "system_name2": "galaxsys/MagicDice"
      },
      {
        "id": "221",
        "name": "Fruit Cocktail",
        "name_cn": "水果鸡尾酒",
        "name_kr": "과일 칵테일",
        "img": "https://static.cdns-stat.com/resources//sitepicstbs/slgames/game_img_2/281_fc.jpg",
        "label": "igrosoft",
        "device": "2",
        "title": "igrosoft",
        "categories": "slots",
        "flash": "0",
        "vertical": "1",
        "bm": "0",
        "demo": "1",
        "localhost": "0",
        "rewriterule": "1",
        "lines": "720",
        "width": "1",
        "wager": "1",
        "bonus": "1",
        "exitButton": "1",
        "disableReload": "0",
        "menu": "",
        "system_name2": "igrosoft/fruitcocktail"
      },
      {
        "id": "219",
        "name": "Keks",
        "name_cn": "蛋糕",
        "name_kr": "켁스",
        "img": "https://static.cdns-stat.com/resources//sitepicstbs/slgames/game_img_2/280_kk.jpg",
        "label": "igrosoft",
        "device": "2",
        "title": "igrosoft",
        "categories": "slots",
        "flash": "0",
        "vertical": "1",
        "bm": "0",
        "demo": "1",
        "localhost": "0",
        "rewriterule": "1",
        "lines": "720",
        "width": "1",
        "wager": "1",
        "bonus": "1",
        "exitButton": "1",
        "disableReload": "0",
        "menu": "",
        "system_name2": "igrosoft/keks"
      },
      {
        "id": "217",
        "name": "Pirate",
        "name_cn": "海盗",
        "name_kr": "해적",
        "img": "https://static.cdns-stat.com/resources//sitepicstbs/slgames/game_img_2/275_pr.jpg",
        "label": "igrosoft",
        "device": "2",
        "title": "igrosoft",
        "categories": "slots",
        "flash": "0",
        "vertical": "1",
        "bm": "0",
        "demo": "1",
        "localhost": "0",
        "rewriterule": "1",
        "lines": "720",
        "width": "1",
        "wager": "1",
        "bonus": "1",
        "exitButton": "1",
        "disableReload": "0",
        "menu": "",
        "system_name2": "igrosoft/pirate"
      },
      {
        "id": "216",
        "name": "Pirate 2",
        "name_cn": "海盗2",
        "name_kr": "해적2",
        "img": "https://static.cdns-stat.com/resources//sitepicstbs/slgames/game_img_2/278_pr2.jpg",
        "label": "igrosoft",
        "device": "2",
        "title": "igrosoft",
        "categories": "slots",
        "flash": "0",
        "vertical": "1",
        "bm": "0",
        "demo": "1",
        "localhost": "0",
        "rewriterule": "1",
        "lines": "720",
        "width": "1",
        "wager": "1",
        "bonus": "1",
        "exitButton": "1",
        "disableReload": "0",
        "menu": "",
        "system_name2": "igrosoft/pirate_2"
      },
      {
        "id": "213",
        "name": "Island 2",
        "name_cn": "岛2",
        "name_kr": "섬 2",
        "img": "https://static.cdns-stat.com/resources//sitepicstbs/slgames/game_img_2/273_is2.jpg",
        "label": "igrosoft",
        "device": "2",
        "title": "igrosoft",
        "categories": "slots",
        "flash": "0",
        "vertical": "1",
        "bm": "0",
        "demo": "1",
        "localhost": "0",
        "rewriterule": "1",
        "lines": "720",
        "width": "1",
        "wager": "1",
        "bonus": "1",
        "exitButton": "1",
        "disableReload": "0",
        "menu": "",
        "system_name2": "igrosoft/island2"
      },
      {
        "id": "211",
        "name": "Island",
        "name_cn": "岛",
        "name_kr": "섬",
        "img": "https://static.cdns-stat.com/resources//sitepicstbs/slgames/game_img_2/271_is.jpg",
        "label": "igrosoft",
        "device": "2",
        "title": "igrosoft",
        "categories": "slots",
        "flash": "0",
        "vertical": "1",
        "bm": "0",
        "demo": "1",
        "localhost": "0",
        "rewriterule": "1",
        "lines": "720",
        "width": "1",
        "wager": "1",
        "bonus": "1",
        "exitButton": "1",
        "disableReload": "0",
        "menu": "",
        "system_name2": "igrosoft/island"
      },
      {
        "id": "209",
        "name": "Rock Climber",
        "name_cn": "攀岩者",
        "name_kr": "암벽 등반자",
        "img": "https://static.cdns-stat.com/resources//sitepicstbs/slgames/game_img_2/269_rc.jpg",
        "label": "igrosoft",
        "device": "2",
        "title": "igrosoft",
        "categories": "slots",
        "flash": "0",
        "vertical": "1",
        "bm": "0",
        "demo": "1",
        "localhost": "0",
        "rewriterule": "1",
        "lines": "720",
        "width": "1",
        "wager": "1",
        "bonus": "1",
        "exitButton": "1",
        "disableReload": "0",
        "menu": "",
        "system_name2": "igrosoft/rockclimber"
      },
      {
        "id": "207",
        "name": "Gnome",
        "name_cn": "侏儒",
        "name_kr": "금언",
        "img": "https://static.cdns-stat.com/resources//sitepicstbs/slgames/game_img_2/268_gn.jpg",
        "label": "igrosoft",
        "device": "2",
        "title": "igrosoft",
        "categories": "slots",
        "flash": "0",
        "vertical": "1",
        "bm": "0",
        "demo": "1",
        "localhost": "0",
        "rewriterule": "1",
        "lines": "720",
        "width": "1",
        "wager": "1",
        "bonus": "1",
        "exitButton": "1",
        "disableReload": "0",
        "menu": "",
        "system_name2": "igrosoft/gnome"
      },
      {
        "id": "205",
        "name": "Resident",
        "name_cn": "间谍兵",
        "name_kr": "레지던트",
        "img": "https://static.cdns-stat.com/resources//sitepicstbs/slgames/game_img_2/265_rs.jpg",
        "label": "igrosoft",
        "device": "2",
        "title": "igrosoft",
        "categories": "slots",
        "flash": "0",
        "vertical": "1",
        "bm": "0",
        "demo": "1",
        "localhost": "0",
        "rewriterule": "1",
        "lines": "720",
        "width": "1",
        "wager": "1",
        "bonus": "1",
        "exitButton": "1",
        "disableReload": "0",
        "menu": "",
        "system_name2": "igrosoft/resident"
      },
      {
        "id": "202",
        "name": "Sweet Life 2",
        "name_cn": "甜蜜生活2",
        "name_kr": "달콤한 인생 2",
        "img": "https://static.cdns-stat.com/resources//sitepicstbs/slgames/game_img_2/264_sl2.jpg",
        "label": "igrosoft",
        "device": "2",
        "title": "igrosoft",
        "categories": "slots",
        "flash": "0",
        "vertical": "1",
        "bm": "0",
        "demo": "1",
        "localhost": "0",
        "rewriterule": "1",
        "lines": "720",
        "width": "1",
        "wager": "1",
        "bonus": "1",
        "exitButton": "1",
        "disableReload": "0",
        "menu": "",
        "system_name2": "igrosoft/swlive2"
      },
      {
        "id": "201",
        "name": "Sweet Life",
        "name_cn": "甜蜜生活",
        "name_kr": "달콤한 인생",
        "img": "https://static.cdns-stat.com/resources//sitepicstbs/slgames/game_img_2/261_sl.jpg",
        "label": "igrosoft",
        "device": "2",
        "title": "igrosoft",
        "categories": "slots",
        "flash": "0",
        "vertical": "1",
        "bm": "0",
        "demo": "1",
        "localhost": "0",
        "rewriterule": "1",
        "lines": "720",
        "width": "1",
        "wager": "1",
        "bonus": "1",
        "exitButton": "1",
        "disableReload": "0",
        "menu": "",
        "system_name2": "igrosoft/swlive"
      },
      {
        "id": "199",
        "name": "Lucky Haunter",
        "name_cn": "幸运狩猎者",
        "name_kr": "럭키 헌터",
        "img": "https://static.cdns-stat.com/resources//sitepicstbs/slgames/game_img_2/259_lh.jpg",
        "label": "igrosoft",
        "device": "2",
        "title": "igrosoft",
        "categories": "slots",
        "flash": "0",
        "vertical": "1",
        "bm": "0",
        "demo": "1",
        "localhost": "0",
        "rewriterule": "1",
        "lines": "720",
        "width": "1",
        "wager": "1",
        "bonus": "1",
        "exitButton": "1",
        "disableReload": "0",
        "menu": "",
        "system_name2": "igrosoft/haunter"
      }
    ]
  }
}